cryptode/cryptode.py
cryptode/lister.py
Cryptode-1.1.1.dist-info/METADATA
Cryptode-1.1.1.dist-info/WHEEL
Cryptode-1.1.1.dist-info/top_level.txt
Cryptode-1.1.1.dist-info/RECORD
