Metadata-Version: 2.1
Name: Cryptode
Version: 1.1.1
Summary: A cryptography framework with 50+ algorithms
Home-page: https://github.com/enginestein/Cryptode
Author: Arya Praneil Pritesh
Author-email: aryapraneil@gmail.com
License: GPL-3.0-only
Project-URL: Source, https://github.com/enginestein/Cryptode
Project-URL: Tracker, https://github.com/enginestein/Cryptode
Classifier: Development Status :: 5 - Production/Stable
Classifier: Programming Language :: Python :: 3 :: Only
Classifier: Programming Language :: Python :: 3
Classifier: Programming Language :: Python :: 3.6
Classifier: Programming Language :: Python :: 3.7
Classifier: Programming Language :: Python :: 3.8
Classifier: Programming Language :: Python :: 3.9
Classifier: Programming Language :: Python :: 3.10
Classifier: Environment :: Console
Classifier: Intended Audience :: Developers
Classifier: Natural Language :: English
Classifier: Operating System :: OS Independent
Requires-Dist: argon2-cffi (==21.3.0)
Requires-Dist: argon2-cffi-bindings (==21.2.0)
Requires-Dist: cffi (==1.15.1)
Requires-Dist: pywin32 (==305)
Requires-Dist: pywin32-ctypes (==0.2.0)
Requires-Dist: bcrypt (==4.0.1)
Requires-Dist: numpy (==1.22.1)
